graphical_models/__init__.py
graphical_models/custom_types.py
graphical_models/classes/__init__.py
graphical_models/classes/semi_markovian.py
graphical_models/classes/cyclic/__init__.py
graphical_models/classes/cyclic/cyclic_graph.py
graphical_models/classes/dags/__init__.py
graphical_models/classes/dags/camdag.py
graphical_models/classes/dags/dag.py
graphical_models/classes/dags/discrete_dag.py
graphical_models/classes/dags/functional_dag.py
graphical_models/classes/dags/gaussdag.py
graphical_models/classes/dags/pdag.py
graphical_models/classes/dags/sample_dag.py
graphical_models/classes/interventions/__init__.py
graphical_models/classes/interventions/interventions.py
graphical_models/classes/mags/__init__.py
graphical_models/classes/mags/ancestral_graph.py
graphical_models/classes/mags/pag.py
graphical_models/classes/undirected/__init__.py
graphical_models/classes/undirected/ggm.py
graphical_models/classes/undirected/undirected_graph.py
graphical_models/rand/__init__.py
graphical_models/rand/graphs.py
graphical_models/utils/__init__.py
graphical_models/utils/core_utils.py
graphical_models-0.1a21.dist-info/LICENSE.txt
graphical_models-0.1a21.dist-info/METADATA
graphical_models-0.1a21.dist-info/WHEEL
graphical_models-0.1a21.dist-info/top_level.txt
graphical_models-0.1a21.dist-info/RECORD
